xnum/__init__.py
xnum/functions.py
xnum/params.py
xnum-1.2.dist-info/licenses/AUTHORS.md
xnum-1.2.dist-info/licenses/LICENSE
xnum-1.2.dist-info/METADATA
xnum-1.2.dist-info/WHEEL
xnum-1.2.dist-info/top_level.txt
xnum-1.2.dist-info/RECORD
