Metadata-Version: 2.4
Name: xnum
Version: 1.2
Summary: XNum: Universal Numeral System Converter
Home-page: https://github.com/openscilab/xnum
Download-URL: https://github.com/openscilab/xnum/tarball/v1.2
Author: XNum Development Team
Author-email: xnum@openscilab.com
License: MIT
Project-URL: Source, https://github.com/openscilab/xnum
Keywords: convert numeral number numeral-system digits
Classifier: Development Status :: 5 - Production/Stable
Classifier: Natural Language :: English
Classifier: License :: OSI Approved :: MIT License
Classifier: Operating System :: OS Independent
Classifier: Programming Language :: Python :: 3.7
Classifier: Programming Language :: Python :: 3.8
Classifier: Programming Language :: Python :: 3.9
Classifier: Programming Language :: Python :: 3.10
Classifier: Programming Language :: Python :: 3.11
Classifier: Programming Language :: Python :: 3.12
Classifier: Programming Language :: Python :: 3.13
Classifier: Programming Language :: Python :: 3.14
Classifier: Intended Audience :: Developers
Classifier: Intended Audience :: Education
Classifier: Intended Audience :: End Users/Desktop
Classifier: Intended Audience :: Manufacturing
Classifier: Topic :: Education
Classifier: Topic :: Text Editors :: Text Processing
Classifier: Topic :: Software Development :: Localization
Requires-Python: >=3.7
License-File: LICENSE
License-File: AUTHORS.md
Dynamic: author
Dynamic: author-email
Dynamic: classifier
Dynamic: description
Dynamic: description-content-type
Dynamic: download-url
Dynamic: home-page
Dynamic: keywords
Dynamic: license
Dynamic: license-file
Dynamic: project-url
Dynamic: requires-python
Dynamic: summary
